{"type":"Topology","arcs":[[[285,294],[5,-20]],[[290,274],[-75,-26]],[[215,248],[-18,38]],[[197,286],[17,32]],[[214,318],[28,4]],[[242,322],[43,-28]],[[298,130],[-45,19]],[[253,149],[37,125]],[[285,294],[-3,17]],[[282,311],[26,-80],[-10,-101]],[[238,154],[15,-5]],[[298,130],[-52,-130]],[[246,0],[-50,128]],[[196,128],[42,26]],[[183,249],[-7,-117]],[[176,132],[-12,-3]],[[164,129],[-54,110]],[[110,239],[73,10]],[[243,364],[-1,-42]],[[214,318],[-193,34]],[[21,352],[222,12]],[[197,286],[-19,16]],[[178,302],[-170,27]],[[8,329],[13,23]],[[164,129],[-40,-23]],[[124,106],[-3,53],[-121,154]],[[0,313],[110,-74]],[[238,154],[-23,94]],[[196,128],[-20,4]],[[183,249],[-5,53]],[[0,313],[8,16]],[[246,0],[-163,18],[41,88]],[[243,364],[39,-53]]],"transform":{"scale":[0.0004074494935063929,0.0003720835302197861],"translate":[123.13378565700009,10.299020608000035]},"objects":{"bgysubmuns-municity-ph0704608":{"type":"GeometryCollection","geometries":[{"arcs":[[0,1,2,3,4,5]],"type":"Polygon","properties":{"ADM4_EN":"Bayog","ADM4_PCODE":"PH0704608001","ADM4_REF":null,"ADM3_EN":"Canlaon City","ADM3_PCODE":"PH0704608","ADM2_EN":"Negros Oriental","ADM2_PCODE":"PH07046","ADM1_EN":"Region VII (Central Visayas)","ADM1_PCODE":"PH07","ADM0_EN":"Philippines (the)","ADM0_PCODE":"PH","date":"2022/11/09","validOn":"2023/11/06","validTo":null,"Shape_Leng":0.134242336709,"Shape_Area":0.000548757067899,"AREA_SQKM":6.64650150907},"id":"PH0704608001"},{"arcs":[[6,7,-1,8,9]],"type":"Polygon","properties":{"ADM4_EN":"Binalbagan","ADM4_PCODE":"PH0704608002","ADM4_REF":null,"ADM3_EN":"Canlaon City","ADM3_PCODE":"PH0704608","ADM2_EN":"Negros Oriental","ADM2_PCODE":"PH07046","ADM1_EN":"Region VII (Central Visayas)","ADM1_PCODE":"PH07","ADM0_EN":"Philippines (the)","ADM0_PCODE":"PH","date":"2022/11/09","validOn":"2023/11/06","validTo":null,"Shape_Leng":0.199863993237,"Shape_Area":0.00104377368994,"AREA_SQKM":12.6430428097},"id":"PH0704608002"},{"arcs":[[10,-7,11,12,13]],"type":"Polygon","properties":{"ADM4_EN":"Bucalan (East Budsalan)","ADM4_PCODE":"PH0704608003","ADM4_REF":null,"ADM3_EN":"Canlaon City","ADM3_PCODE":"PH0704608","ADM2_EN":"Negros Oriental","ADM2_PCODE":"PH07046","ADM1_EN":"Region VII (Central Visayas)","ADM1_PCODE":"PH07","ADM0_EN":"Philippines (the)","ADM0_PCODE":"PH","date":"2022/11/09","validOn":"2023/11/06","validTo":null,"Shape_Leng":0.187355280892,"Shape_Area":0.00143827852746,"AREA_SQKM":17.4243155992},"id":"PH0704608003"},{"arcs":[[14,15,16,17]],"type":"Polygon","properties":{"ADM4_EN":"Linothangan","ADM4_PCODE":"PH0704608004","ADM4_REF":null,"ADM3_EN":"Canlaon City","ADM3_PCODE":"PH0704608","ADM2_EN":"Negros Oriental","ADM2_PCODE":"PH07046","ADM1_EN":"Region VII (Central Visayas)","ADM1_PCODE":"PH07","ADM0_EN":"Philippines (the)","ADM0_PCODE":"PH","date":"2022/11/09","validOn":"2023/11/06","validTo":null,"Shape_Leng":0.156190019569,"Shape_Area":0.000653859756032,"AREA_SQKM":7.92022952271},"id":"PH0704608004"},{"arcs":[[18,-5,19,20]],"type":"Polygon","properties":{"ADM4_EN":"Lumapao","ADM4_PCODE":"PH0704608005","ADM4_REF":null,"ADM3_EN":"Canlaon City","ADM3_PCODE":"PH0704608","ADM2_EN":"Negros Oriental","ADM2_PCODE":"PH07046","ADM1_EN":"Region VII (Central Visayas)","ADM1_PCODE":"PH07","ADM0_EN":"Philippines (the)","ADM0_PCODE":"PH","date":"2022/11/09","validOn":"2023/11/06","validTo":null,"Shape_Leng":0.234884831566,"Shape_Area":0.00082235534454,"AREA_SQKM":9.95950678742},"id":"PH0704608005"},{"arcs":[[-4,21,22,23,-20]],"type":"Polygon","properties":{"ADM4_EN":"Malaiba","ADM4_PCODE":"PH0704608006","ADM4_REF":null,"ADM3_EN":"Canlaon City","ADM3_PCODE":"PH0704608","ADM2_EN":"Negros Oriental","ADM2_PCODE":"PH07046","ADM1_EN":"Region VII (Central Visayas)","ADM1_PCODE":"PH07","ADM0_EN":"Philippines (the)","ADM0_PCODE":"PH","date":"2022/11/09","validOn":"2023/11/06","validTo":null,"Shape_Leng":0.21228290987,"Shape_Area":0.00103775402023,"AREA_SQKM":12.5685715678},"id":"PH0704608006"},{"arcs":[[-17,24,25,26]],"type":"Polygon","properties":{"ADM4_EN":"Masulog","ADM4_PCODE":"PH0704608007","ADM4_REF":null,"ADM3_EN":"Canlaon City","ADM3_PCODE":"PH0704608","ADM2_EN":"Negros Oriental","ADM2_PCODE":"PH07046","ADM1_EN":"Region VII (Central Visayas)","ADM1_PCODE":"PH07","ADM0_EN":"Philippines (the)","ADM0_PCODE":"PH","date":"2022/11/09","validOn":"2023/11/06","validTo":null,"Shape_Leng":0.245360577366,"Shape_Area":0.00131673997743,"AREA_SQKM":15.949708847},"id":"PH0704608007"},{"arcs":[[-8,-11,27,-2]],"type":"Polygon","properties":{"ADM4_EN":"Panubigan","ADM4_PCODE":"PH0704608008","ADM4_REF":null,"ADM3_EN":"Canlaon City","ADM3_PCODE":"PH0704608","ADM2_EN":"Negros Oriental","ADM2_PCODE":"PH07046","ADM1_EN":"Region VII (Central Visayas)","ADM1_PCODE":"PH07","ADM0_EN":"Philippines (the)","ADM0_PCODE":"PH","date":"2022/11/09","validOn":"2023/11/06","validTo":null,"Shape_Leng":0.170507393163,"Shape_Area":0.000683615702575,"AREA_SQKM":8.28055740798},"id":"PH0704608008"},{"arcs":[[-3,-28,-14,28,-15,29,-22]],"type":"Polygon","properties":{"ADM4_EN":"Mabigo (Pob.)","ADM4_PCODE":"PH0704608009","ADM4_REF":null,"ADM3_EN":"Canlaon City","ADM3_PCODE":"PH0704608","ADM2_EN":"Negros Oriental","ADM2_PCODE":"PH07046","ADM1_EN":"Region VII (Central Visayas)","ADM1_PCODE":"PH07","ADM0_EN":"Philippines (the)","ADM0_PCODE":"PH","date":"2022/11/09","validOn":"2023/11/06","validTo":null,"Shape_Leng":0.184557738012,"Shape_Area":0.000917992784656,"AREA_SQKM":11.11971781},"id":"PH0704608009"},{"arcs":[[-30,-18,-27,30,-23]],"type":"Polygon","properties":{"ADM4_EN":"Pula","ADM4_PCODE":"PH0704608010","ADM4_REF":null,"ADM3_EN":"Canlaon City","ADM3_PCODE":"PH0704608","ADM2_EN":"Negros Oriental","ADM2_PCODE":"PH07046","ADM1_EN":"Region VII (Central Visayas)","ADM1_PCODE":"PH07","ADM0_EN":"Philippines (the)","ADM0_PCODE":"PH","date":"2022/11/09","validOn":"2023/11/06","validTo":null,"Shape_Leng":0.196258588341,"Shape_Area":0.00141944471742,"AREA_SQKM":17.1922200818},"id":"PH0704608010"},{"arcs":[[-13,31,-25,-16,-29]],"type":"Polygon","properties":{"ADM4_EN":"Budlasan (West Budlasan)","ADM4_PCODE":"PH0704608011","ADM4_REF":null,"ADM3_EN":"Canlaon City","ADM3_PCODE":"PH0704608","ADM2_EN":"Negros Oriental","ADM2_PCODE":"PH07046","ADM1_EN":"Region VII (Central Visayas)","ADM1_PCODE":"PH07","ADM0_EN":"Philippines (the)","ADM0_PCODE":"PH","date":"2022/11/09","validOn":"2023/11/06","validTo":null,"Shape_Leng":0.237866368246,"Shape_Area":0.00191422505202,"AREA_SQKM":23.1911141235},"id":"PH0704608011"},{"arcs":[[-9,-6,-19,32]],"type":"Polygon","properties":{"ADM4_EN":"Ninoy Aquino","ADM4_PCODE":"PH0704608012","ADM4_REF":null,"ADM3_EN":"Canlaon City","ADM3_PCODE":"PH0704608","ADM2_EN":"Negros Oriental","ADM2_PCODE":"PH07046","ADM1_EN":"Region VII (Central Visayas)","ADM1_PCODE":"PH07","ADM0_EN":"Philippines (the)","ADM0_PCODE":"PH","date":"2022/11/09","validOn":"2023/11/06","validTo":null,"Shape_Leng":0.110659049574,"Shape_Area":0.00038172104239,"AREA_SQKM":4.62310826399},"id":"PH0704608012"}]}}}