{"type":"Topology","arcs":[[[656,391],[-6,-75]],[[650,316],[-59,-7]],[[591,309],[-23,33]],[[568,342],[15,63]],[[583,405],[73,-14]],[[532,86],[3,-72],[-76,-1]],[[459,13],[16,109]],[[475,122],[32,1],[25,-37]],[[522,542],[-5,-37],[63,-44]],[[580,461],[3,-56]],[[568,342],[-157,25]],[[411,367],[-19,100],[5,109]],[[397,576],[125,-34]],[[459,13],[-90,4]],[[369,17],[26,90]],[[395,107],[80,15]],[[557,251],[-35,-85],[-54,19],[-74,-11]],[[394,174],[4,99]],[[398,273],[65,-3],[83,12],[11,-31]],[[706,519],[-47,-19]],[[659,500],[-79,-39]],[[522,542],[117,-22],[67,-1]],[[671,391],[-15,0]],[[659,500],[12,-109]],[[706,519],[25,-106],[-8,-46]],[[723,367],[-52,24]],[[591,309],[-8,-79]],[[583,230],[-26,21]],[[398,273],[-53,-5],[-14,34],[80,65]],[[650,316],[48,-73]],[[698,243],[-8,-55]],[[690,188],[-104,-3]],[[586,185],[-3,45]],[[690,188],[-59,-48],[-35,13]],[[596,153],[-10,32]],[[723,367],[-22,-63],[-3,-61]],[[596,153],[-44,-23],[-20,-44]],[[395,107],[-1,67]],[[369,17],[-242,0],[-83,-17],[-34,299],[-10,314],[269,-35],[128,-2]]],"transform":{"scale":[0.00034252177838583906,0.0002326405628057989],"translate":[121.243548991,12.756897567000067]},"objects":{"bgysubmuns-municity-ph1705202":{"type":"GeometryCollection","geometries":[{"arcs":[[0,1,2,3,4]],"type":"Polygon","properties":{"ADM4_EN":"Alcadesma","ADM4_PCODE":"PH1705202001","ADM4_REF":null,"ADM3_EN":"Bansud","ADM3_PCODE":"PH1705202","ADM2_EN":"Oriental Mindoro","ADM2_PCODE":"PH17052","ADM1_EN":"Mimaropa Region","ADM1_PCODE":"PH17","ADM0_EN":"Philippines (the)","ADM0_PCODE":"PH","date":"2022/11/09","validOn":"2023/11/06","validTo":null,"Shape_Leng":0.101907580181,"Shape_Area":0.000533196300645,"AREA_SQKM":6.40325883832},"id":"PH1705202001"},{"arcs":[[5,6,7]],"type":"Polygon","properties":{"ADM4_EN":"Bato","ADM4_PCODE":"PH1705202003","ADM4_REF":null,"ADM3_EN":"Bansud","ADM3_PCODE":"PH1705202","ADM2_EN":"Oriental Mindoro","ADM2_PCODE":"PH17052","ADM1_EN":"Mimaropa Region","ADM1_PCODE":"PH17","ADM0_EN":"Philippines (the)","ADM0_PCODE":"PH","date":"2022/11/09","validOn":"2023/11/06","validTo":null,"Shape_Leng":0.0970141839989,"Shape_Area":0.000566968398082,"AREA_SQKM":6.81065826417},"id":"PH1705202003"},{"arcs":[[8,9,-4,10,11,12]],"type":"Polygon","properties":{"ADM4_EN":"Conrazon","ADM4_PCODE":"PH1705202004","ADM4_REF":null,"ADM3_EN":"Bansud","ADM3_PCODE":"PH1705202","ADM2_EN":"Oriental Mindoro","ADM2_PCODE":"PH17052","ADM1_EN":"Mimaropa Region","ADM1_PCODE":"PH17","ADM0_EN":"Philippines (the)","ADM0_PCODE":"PH","date":"2022/11/09","validOn":"2023/11/06","validTo":null,"Shape_Leng":0.208923769872,"Shape_Area":0.00256177824337,"AREA_SQKM":30.762370631},"id":"PH1705202004"},{"arcs":[[-7,13,14,15]],"type":"Polygon","properties":{"ADM4_EN":"Malo","ADM4_PCODE":"PH1705202005","ADM4_REF":null,"ADM3_EN":"Bansud","ADM3_PCODE":"PH1705202","ADM2_EN":"Oriental Mindoro","ADM2_PCODE":"PH17052","ADM1_EN":"Mimaropa Region","ADM1_PCODE":"PH17","ADM0_EN":"Philippines (the)","ADM0_PCODE":"PH","date":"2022/11/09","validOn":"2023/11/06","validTo":null,"Shape_Leng":0.114027041013,"Shape_Area":0.000650892283273,"AREA_SQKM":7.81878495785},"id":"PH1705202005"},{"arcs":[[16,17,18]],"type":"Polygon","properties":{"ADM4_EN":"Manihala","ADM4_PCODE":"PH1705202006","ADM4_REF":null,"ADM3_EN":"Bansud","ADM3_PCODE":"PH1705202","ADM2_EN":"Oriental Mindoro","ADM2_PCODE":"PH17052","ADM1_EN":"Mimaropa Region","ADM1_PCODE":"PH17","ADM0_EN":"Philippines (the)","ADM0_PCODE":"PH","date":"2022/11/09","validOn":"2023/11/06","validTo":null,"Shape_Leng":0.152889820622,"Shape_Area":0.00108765097444,"AREA_SQKM":13.0633774095},"id":"PH1705202006"},{"arcs":[[19,20,-9,21]],"type":"Polygon","properties":{"ADM4_EN":"Pag-Asa","ADM4_PCODE":"PH1705202007","ADM4_REF":null,"ADM3_EN":"Bansud","ADM3_PCODE":"PH1705202","ADM2_EN":"Oriental Mindoro","ADM2_PCODE":"PH17052","ADM1_EN":"Mimaropa Region","ADM1_PCODE":"PH17","ADM0_EN":"Philippines (the)","ADM0_PCODE":"PH","date":"2022/11/09","validOn":"2023/11/06","validTo":null,"Shape_Leng":0.162050639641,"Shape_Area":0.000681690511299,"AREA_SQKM":8.1854858165},"id":"PH1705202007"},{"arcs":[[22,-5,-10,-21,23]],"type":"Polygon","properties":{"ADM4_EN":"Poblacion","ADM4_PCODE":"PH1705202008","ADM4_REF":null,"ADM3_EN":"Bansud","ADM3_PCODE":"PH1705202","ADM2_EN":"Oriental Mindoro","ADM2_PCODE":"PH17052","ADM1_EN":"Mimaropa Region","ADM1_PCODE":"PH17","ADM0_EN":"Philippines (the)","ADM0_PCODE":"PH","date":"2022/11/09","validOn":"2023/11/06","validTo":null,"Shape_Leng":0.109737552284,"Shape_Area":0.000487847803273,"AREA_SQKM":5.85825240366},"id":"PH1705202008"},{"arcs":[[24,25,-24,-20]],"type":"Polygon","properties":{"ADM4_EN":"Proper Bansud","ADM4_PCODE":"PH1705202009","ADM4_REF":null,"ADM3_EN":"Bansud","ADM3_PCODE":"PH1705202","ADM2_EN":"Oriental Mindoro","ADM2_PCODE":"PH17052","ADM1_EN":"Mimaropa Region","ADM1_PCODE":"PH17","ADM0_EN":"Philippines (the)","ADM0_PCODE":"PH","date":"2022/11/09","validOn":"2023/11/06","validTo":null,"Shape_Leng":0.117977080299,"Shape_Area":0.000572062920036,"AREA_SQKM":6.86952380022},"id":"PH1705202009"},{"arcs":[[-3,26,27,-19,28,-11]],"type":"Polygon","properties":{"ADM4_EN":"Rosacara","ADM4_PCODE":"PH1705202010","ADM4_REF":null,"ADM3_EN":"Bansud","ADM3_PCODE":"PH1705202","ADM2_EN":"Oriental Mindoro","ADM2_PCODE":"PH17052","ADM1_EN":"Mimaropa Region","ADM1_PCODE":"PH17","ADM0_EN":"Philippines (the)","ADM0_PCODE":"PH","date":"2022/11/09","validOn":"2023/11/06","validTo":null,"Shape_Leng":0.218300416308,"Shape_Area":0.00159088939617,"AREA_SQKM":19.1061617977},"id":"PH1705202010"},{"arcs":[[29,30,31,32,-27,-2]],"type":"Polygon","properties":{"ADM4_EN":"Salcedo","ADM4_PCODE":"PH1705202011","ADM4_REF":null,"ADM3_EN":"Bansud","ADM3_PCODE":"PH1705202","ADM2_EN":"Oriental Mindoro","ADM2_PCODE":"PH17052","ADM1_EN":"Mimaropa Region","ADM1_PCODE":"PH17","ADM0_EN":"Philippines (the)","ADM0_PCODE":"PH","date":"2022/11/09","validOn":"2023/11/06","validTo":null,"Shape_Leng":0.129789848635,"Shape_Area":0.000999803931872,"AREA_SQKM":12.0080561099},"id":"PH1705202011"},{"arcs":[[33,34,-32]],"type":"Polygon","properties":{"ADM4_EN":"Sumagui","ADM4_PCODE":"PH1705202012","ADM4_REF":null,"ADM3_EN":"Bansud","ADM3_PCODE":"PH1705202","ADM2_EN":"Oriental Mindoro","ADM2_PCODE":"PH17052","ADM1_EN":"Mimaropa Region","ADM1_PCODE":"PH17","ADM0_EN":"Philippines (the)","ADM0_PCODE":"PH","date":"2022/11/09","validOn":"2023/11/06","validTo":null,"Shape_Leng":0.0969442838297,"Shape_Area":0.000335855004314,"AREA_SQKM":4.0340425503},"id":"PH1705202012"},{"arcs":[[35,-30,-1,-23,-26]],"type":"Polygon","properties":{"ADM4_EN":"Proper Tiguisan","ADM4_PCODE":"PH1705202013","ADM4_REF":null,"ADM3_EN":"Bansud","ADM3_PCODE":"PH1705202","ADM2_EN":"Oriental Mindoro","ADM2_PCODE":"PH17052","ADM1_EN":"Mimaropa Region","ADM1_PCODE":"PH17","ADM0_EN":"Philippines (the)","ADM0_PCODE":"PH","date":"2022/11/09","validOn":"2023/11/06","validTo":null,"Shape_Leng":0.103888754808,"Shape_Area":0.000468407307608,"AREA_SQKM":5.62534838142},"id":"PH1705202013"},{"arcs":[[-33,-35,36,-8,-16,37,-17,-28]],"type":"Polygon","properties":{"ADM4_EN":"Villa Pag-Asa","ADM4_PCODE":"PH1705202014","ADM4_REF":null,"ADM3_EN":"Bansud","ADM3_PCODE":"PH1705202","ADM2_EN":"Oriental Mindoro","ADM2_PCODE":"PH17052","ADM1_EN":"Mimaropa Region","ADM1_PCODE":"PH17","ADM0_EN":"Philippines (the)","ADM0_PCODE":"PH","date":"2022/11/09","validOn":"2023/11/06","validTo":null,"Shape_Leng":0.215134237902,"Shape_Area":0.0011727391684,"AREA_SQKM":14.0862154695},"id":"PH1705202014"},{"arcs":[[-12,-29,-18,-38,-15,38]],"type":"Polygon","properties":{"ADM4_EN":"Forest Land under Jurisdiction of Bansud, Oriental Mindoro","ADM4_PCODE":"PH1705202901","ADM4_REF":null,"ADM3_EN":"Bansud","ADM3_PCODE":"PH1705202","ADM2_EN":"Oriental Mindoro","ADM2_PCODE":"PH17052","ADM1_EN":"Mimaropa Region","ADM1_PCODE":"PH17","ADM0_EN":"Philippines (the)","ADM0_PCODE":"PH","date":"2022/11/09","validOn":"2023/11/06","validTo":null,"Shape_Leng":0.562921156473,"Shape_Area":0.0170478862782,"AREA_SQKM":204.740416102},"id":"PH1705202901"}]}}}