{"type":"Topology","arcs":[[[162,272],[-84,-51]],[[78,221],[-55,32]],[[23,253],[52,70]],[[75,323],[100,-4],[-13,-47]],[[353,319],[-14,-47],[-120,-24],[-57,24]],[[75,323],[-15,13]],[[60,336],[60,115],[28,80],[180,-1],[1,-191],[24,-20]],[[413,62],[-1,-62],[-259,0]],[[153,0],[21,142]],[[174,142],[66,-11],[32,-26],[36,17],[69,-50],[36,-10]],[[153,0],[-41,0],[-88,181]],[[24,181],[17,21]],[[41,202],[37,19]],[[78,221],[38,-5],[58,-74]],[[353,319],[60,-30],[0,-227]],[[41,202],[-32,24]],[[9,226],[14,27]],[[9,226],[-9,-1]],[[0,225],[5,55],[55,56]],[[24,181],[-24,44]]],"transform":{"scale":[0.00014136548910420935,0.00013105925423725358],"translate":[125.51282448300003,8.996399591000056]},"objects":{"bgysubmuns-municity-ph1600208":{"type":"GeometryCollection","geometries":[{"arcs":[[0,1,2,3]],"type":"Polygon","properties":{"ADM4_EN":"Buhang","ADM4_PCODE":"PH1600208001","ADM4_REF":null,"ADM3_EN":"Magallanes","ADM3_PCODE":"PH1600208","ADM2_EN":"Agusan del Norte","ADM2_PCODE":"PH16002","ADM1_EN":"Region XIII (Caraga)","ADM1_PCODE":"PH16","ADM0_EN":"Philippines (the)","ADM0_PCODE":"PH","date":"2022/11/09","validOn":"2023/11/06","validTo":null,"Shape_Leng":0.0592327452251,"Shape_Area":0.000163681137129,"AREA_SQKM":1.99043406652},"id":"PH1600208001"},{"arcs":[[4,-4,5,6]],"type":"Polygon","properties":{"ADM4_EN":"Caloc-an","ADM4_PCODE":"PH1600208002","ADM4_REF":null,"ADM3_EN":"Magallanes","ADM3_PCODE":"PH1600208","ADM2_EN":"Agusan del Norte","ADM2_PCODE":"PH16002","ADM1_EN":"Region XIII (Caraga)","ADM1_PCODE":"PH16","ADM0_EN":"Philippines (the)","ADM0_PCODE":"PH","date":"2022/11/09","validOn":"2023/11/06","validTo":null,"Shape_Leng":0.156981536394,"Shape_Area":0.00105164556662,"AREA_SQKM":12.7879332192},"id":"PH1600208002"},{"arcs":[[7,8,9]],"type":"Polygon","properties":{"ADM4_EN":"Guiasan","ADM4_PCODE":"PH1600208003","ADM4_REF":null,"ADM3_EN":"Magallanes","ADM3_PCODE":"PH1600208","ADM2_EN":"Agusan del Norte","ADM2_PCODE":"PH16002","ADM1_EN":"Region XIII (Caraga)","ADM1_PCODE":"PH16","ADM0_EN":"Philippines (the)","ADM0_PCODE":"PH","date":"2022/11/09","validOn":"2023/11/06","validTo":null,"Shape_Leng":0.102338095114,"Shape_Area":0.000508787900529,"AREA_SQKM":6.18756651798},"id":"PH1600208003"},{"arcs":[[-9,10,11,12,13]],"type":"Polygon","properties":{"ADM4_EN":"Poblacion","ADM4_PCODE":"PH1600208005","ADM4_REF":null,"ADM3_EN":"Magallanes","ADM3_PCODE":"PH1600208","ADM2_EN":"Agusan del Norte","ADM2_PCODE":"PH16002","ADM1_EN":"Region XIII (Caraga)","ADM1_PCODE":"PH16","ADM0_EN":"Philippines (the)","ADM0_PCODE":"PH","date":"2022/11/09","validOn":"2023/11/06","validTo":null,"Shape_Leng":0.0940138479801,"Shape_Area":0.000339727136524,"AREA_SQKM":4.13146261775},"id":"PH1600208005"},{"arcs":[[-10,-14,-1,-5,14]],"type":"Polygon","properties":{"ADM4_EN":"Taod-oy","ADM4_PCODE":"PH1600208008","ADM4_REF":null,"ADM3_EN":"Magallanes","ADM3_PCODE":"PH1600208","ADM2_EN":"Agusan del Norte","ADM2_PCODE":"PH16002","ADM1_EN":"Region XIII (Caraga)","ADM1_PCODE":"PH16","ADM0_EN":"Philippines (the)","ADM0_PCODE":"PH","date":"2022/11/09","validOn":"2023/11/06","validTo":null,"Shape_Leng":0.16171188853,"Shape_Area":0.000840782207214,"AREA_SQKM":10.2245790373},"id":"PH1600208008"},{"arcs":[[-2,-13,15,16]],"type":"Polygon","properties":{"ADM4_EN":"Marcos","ADM4_PCODE":"PH1600208009","ADM4_REF":null,"ADM3_EN":"Magallanes","ADM3_PCODE":"PH1600208","ADM2_EN":"Agusan del Norte","ADM2_PCODE":"PH16002","ADM1_EN":"Region XIII (Caraga)","ADM1_PCODE":"PH16","ADM0_EN":"Philippines (the)","ADM0_PCODE":"PH","date":"2022/11/09","validOn":"2023/11/06","validTo":null,"Shape_Leng":0.029829968921,"Shape_Area":0.0000380949300638,"AREA_SQKM":0.463260061672},"id":"PH1600208009"},{"arcs":[[-3,-17,17,18,-6]],"type":"Polygon","properties":{"ADM4_EN":"Santo Niño","ADM4_PCODE":"PH1600208010","ADM4_REF":"Santo Nino","ADM3_EN":"Magallanes","ADM3_PCODE":"PH1600208","ADM2_EN":"Agusan del Norte","ADM2_PCODE":"PH16002","ADM1_EN":"Region XIII (Caraga)","ADM1_PCODE":"PH16","ADM0_EN":"Philippines (the)","ADM0_PCODE":"PH","date":"2022/11/09","validOn":"2023/11/06","validTo":null,"Shape_Leng":0.0458529412782,"Shape_Area":0.00005790697285,"AREA_SQKM":0.70417343093},"id":"PH1600208010"},{"arcs":[[-16,-12,19,-18]],"type":"Polygon","properties":{"ADM4_EN":"Santo Rosario","ADM4_PCODE":"PH1600208011","ADM4_REF":null,"ADM3_EN":"Magallanes","ADM3_PCODE":"PH1600208","ADM2_EN":"Agusan del Norte","ADM2_PCODE":"PH16002","ADM1_EN":"Region XIII (Caraga)","ADM1_PCODE":"PH16","ADM0_EN":"Philippines (the)","ADM0_PCODE":"PH","date":"2022/11/09","validOn":"2023/11/06","validTo":null,"Shape_Leng":0.0189204977235,"Shape_Area":0.0000111612610796,"AREA_SQKM":0.135729451447},"id":"PH1600208011"}]}}}