{"type":"Topology","arcs":[[[76,202],[-28,-26]],[[48,176],[-13,-13]],[[35,163],[-35,5]],[[0,168],[60,61]],[[60,229],[16,-27]],[[29,117],[177,-10]],[[206,107],[15,-107]],[[221,0],[-203,120]],[[18,120],[11,-3]],[[35,163],[-6,-46]],[[18,120],[-18,48]],[[313,429],[10,-35]],[[323,394],[-56,-55]],[[267,339],[-15,6]],[[252,345],[61,84]],[[267,339],[17,-59]],[[284,280],[-57,-39]],[[227,241],[-57,41]],[[170,282],[82,63]],[[368,402],[-45,-8]],[[313,429],[55,-27]],[[352,278],[-68,2]],[[368,402],[-16,-124]],[[227,241],[-37,-69]],[[190,172],[-82,80]],[[108,252],[62,30]],[[190,124],[16,-17]],[[48,176],[142,-52]],[[190,172],[0,-48]],[[76,202],[12,46]],[[88,248],[20,4]],[[60,229],[28,19]],[[352,278],[-131,-278]]],"transform":{"scale":[0.00020603776630423454,0.0001701682214451517],"translate":[120.50816900800011,17.408057186000065]},"objects":{"bgysubmuns-municity-ph0102913":{"type":"GeometryCollection","geometries":[{"arcs":[[0,1,2,3,4]],"type":"Polygon","properties":{"ADM4_EN":"Balaweg","ADM4_PCODE":"PH0102913001","ADM4_REF":null,"ADM3_EN":"Nagbukel","ADM3_PCODE":"PH0102913","ADM2_EN":"Ilocos Sur","ADM2_PCODE":"PH01029","ADM1_EN":"Region I (Ilocos Region)","ADM1_PCODE":"PH01","ADM0_EN":"Philippines (the)","ADM0_PCODE":"PH","date":"2022/11/09","validOn":"2023/11/06","validTo":null,"Shape_Leng":0.0454912351943,"Shape_Area":0.0000830169787897,"AREA_SQKM":0.976058893251},"id":"PH0102913001"},{"arcs":[[5,6,7,8]],"type":"Polygon","properties":{"ADM4_EN":"Bandril","ADM4_PCODE":"PH0102913002","ADM4_REF":null,"ADM3_EN":"Nagbukel","ADM3_PCODE":"PH0102913","ADM2_EN":"Ilocos Sur","ADM2_PCODE":"PH01029","ADM1_EN":"Region I (Ilocos Region)","ADM1_PCODE":"PH01","ADM0_EN":"Philippines (the)","ADM0_PCODE":"PH","date":"2022/11/09","validOn":"2023/11/06","validTo":null,"Shape_Leng":0.119453136238,"Shape_Area":0.000668484391395,"AREA_SQKM":7.86056137985},"id":"PH0102913002"},{"arcs":[[9,-9,10,-3]],"type":"Polygon","properties":{"ADM4_EN":"Bantugo","ADM4_PCODE":"PH0102913003","ADM4_REF":null,"ADM3_EN":"Nagbukel","ADM3_PCODE":"PH0102913","ADM2_EN":"Ilocos Sur","ADM2_PCODE":"PH01029","ADM1_EN":"Region I (Ilocos Region)","ADM1_PCODE":"PH01","ADM0_EN":"Philippines (the)","ADM0_PCODE":"PH","date":"2022/11/09","validOn":"2023/11/06","validTo":null,"Shape_Leng":0.0281209127087,"Shape_Area":0.0000324204171008,"AREA_SQKM":0.38119364414},"id":"PH0102913003"},{"arcs":[[11,12,13,14]],"type":"Polygon","properties":{"ADM4_EN":"Cadacad","ADM4_PCODE":"PH0102913004","ADM4_REF":null,"ADM3_EN":"Nagbukel","ADM3_PCODE":"PH0102913","ADM2_EN":"Ilocos Sur","ADM2_PCODE":"PH01029","ADM1_EN":"Region I (Ilocos Region)","ADM1_PCODE":"PH01","ADM0_EN":"Philippines (the)","ADM0_PCODE":"PH","date":"2022/11/09","validOn":"2023/11/06","validTo":null,"Shape_Leng":0.0574815250489,"Shape_Area":0.000140992938855,"AREA_SQKM":1.65738719825},"id":"PH0102913004"},{"arcs":[[15,16,17,18,-14]],"type":"Polygon","properties":{"ADM4_EN":"Casilagan","ADM4_PCODE":"PH0102913005","ADM4_REF":null,"ADM3_EN":"Nagbukel","ADM3_PCODE":"PH0102913","ADM2_EN":"Ilocos Sur","ADM2_PCODE":"PH01029","ADM1_EN":"Region I (Ilocos Region)","ADM1_PCODE":"PH01","ADM0_EN":"Philippines (the)","ADM0_PCODE":"PH","date":"2022/11/09","validOn":"2023/11/06","validTo":null,"Shape_Leng":0.0666175388228,"Shape_Area":0.000244617607272,"AREA_SQKM":2.87581030536},"id":"PH0102913005"},{"arcs":[[19,-12,20]],"type":"Polygon","properties":{"ADM4_EN":"Cosocos","ADM4_PCODE":"PH0102913006","ADM4_REF":null,"ADM3_EN":"Nagbukel","ADM3_PCODE":"PH0102913","ADM2_EN":"Ilocos Sur","ADM2_PCODE":"PH01029","ADM1_EN":"Region I (Ilocos Region)","ADM1_PCODE":"PH01","ADM0_EN":"Philippines (the)","ADM0_PCODE":"PH","date":"2022/11/09","validOn":"2023/11/06","validTo":null,"Shape_Leng":0.0557382450614,"Shape_Area":0.000186836520433,"AREA_SQKM":2.19619000058},"id":"PH0102913006"},{"arcs":[[21,-16,-13,-20,22]],"type":"Polygon","properties":{"ADM4_EN":"Lapting","ADM4_PCODE":"PH0102913007","ADM4_REF":null,"ADM3_EN":"Nagbukel","ADM3_PCODE":"PH0102913","ADM2_EN":"Ilocos Sur","ADM2_PCODE":"PH01029","ADM1_EN":"Region I (Ilocos Region)","ADM1_PCODE":"PH01","ADM0_EN":"Philippines (the)","ADM0_PCODE":"PH","date":"2022/11/09","validOn":"2023/11/06","validTo":null,"Shape_Leng":0.0745592759035,"Shape_Area":0.000311446171112,"AREA_SQKM":3.66128265915},"id":"PH0102913007"},{"arcs":[[23,24,25,-18]],"type":"Polygon","properties":{"ADM4_EN":"Mapisi","ADM4_PCODE":"PH0102913008","ADM4_REF":null,"ADM3_EN":"Nagbukel","ADM3_PCODE":"PH0102913","ADM2_EN":"Ilocos Sur","ADM2_PCODE":"PH01029","ADM1_EN":"Region I (Ilocos Region)","ADM1_PCODE":"PH01","ADM0_EN":"Philippines (the)","ADM0_PCODE":"PH","date":"2022/11/09","validOn":"2023/11/06","validTo":null,"Shape_Leng":0.0720004761498,"Shape_Area":0.000273370700483,"AREA_SQKM":3.21400707964},"id":"PH0102913008"},{"arcs":[[26,-6,-10,-2,27]],"type":"Polygon","properties":{"ADM4_EN":"Mission","ADM4_PCODE":"PH0102913009","ADM4_REF":null,"ADM3_EN":"Nagbukel","ADM3_PCODE":"PH0102913","ADM2_EN":"Ilocos Sur","ADM2_PCODE":"PH01029","ADM1_EN":"Region I (Ilocos Region)","ADM1_PCODE":"PH01","ADM0_EN":"Philippines (the)","ADM0_PCODE":"PH","date":"2022/11/09","validOn":"2023/11/06","validTo":null,"Shape_Leng":0.0858302966217,"Shape_Area":0.000258950495102,"AREA_SQKM":3.04475564692},"id":"PH0102913009"},{"arcs":[[28,-28,-1,29,30,-25]],"type":"Polygon","properties":{"ADM4_EN":"Poblacion East","ADM4_PCODE":"PH0102913010","ADM4_REF":null,"ADM3_EN":"Nagbukel","ADM3_PCODE":"PH0102913","ADM2_EN":"Ilocos Sur","ADM2_PCODE":"PH01029","ADM1_EN":"Region I (Ilocos Region)","ADM1_PCODE":"PH01","ADM0_EN":"Philippines (the)","ADM0_PCODE":"PH","date":"2022/11/09","validOn":"2023/11/06","validTo":null,"Shape_Leng":0.0879904499028,"Shape_Area":0.000294792951099,"AREA_SQKM":3.46603505471},"id":"PH0102913010"},{"arcs":[[-30,-5,31]],"type":"Polygon","properties":{"ADM4_EN":"Poblacion West","ADM4_PCODE":"PH0102913011","ADM4_REF":null,"ADM3_EN":"Nagbukel","ADM3_PCODE":"PH0102913","ADM2_EN":"Ilocos Sur","ADM2_PCODE":"PH01029","ADM1_EN":"Region I (Ilocos Region)","ADM1_PCODE":"PH01","ADM0_EN":"Philippines (the)","ADM0_PCODE":"PH","date":"2022/11/09","validOn":"2023/11/06","validTo":null,"Shape_Leng":0.0222379245089,"Shape_Area":0.0000239372623828,"AREA_SQKM":0.281429694935},"id":"PH0102913011"},{"arcs":[[32,-7,-27,-29,-24,-17,-22]],"type":"Polygon","properties":{"ADM4_EN":"Taleb","ADM4_PCODE":"PH0102913012","ADM4_REF":null,"ADM3_EN":"Nagbukel","ADM3_PCODE":"PH0102913","ADM2_EN":"Ilocos Sur","ADM2_PCODE":"PH01029","ADM1_EN":"Region I (Ilocos Region)","ADM1_PCODE":"PH01","ADM0_EN":"Philippines (the)","ADM0_PCODE":"PH","date":"2022/11/09","validOn":"2023/11/06","validTo":null,"Shape_Leng":0.141050319767,"Shape_Area":0.00108909980926,"AREA_SQKM":12.8054137022},"id":"PH0102913012"}]}}}